discord/ext/vbu/__init__.py
voxelbotutils/__init__.py
voxelbotutils/__main__.py
voxelbotutils/runner.py
voxelbotutils/cogs/__init__.py
voxelbotutils/cogs/bot_stats.py
voxelbotutils/cogs/command_event.py
voxelbotutils/cogs/connect_event.py
voxelbotutils/cogs/error_handler.py
voxelbotutils/cogs/general_analytics.py
voxelbotutils/cogs/help_command.py
voxelbotutils/cogs/interaction_handler.py
voxelbotutils/cogs/misc_commands.py
voxelbotutils/cogs/owner_only.py
voxelbotutils/cogs/presence_auto_updater.py
voxelbotutils/cogs/simple_bot_settings.py
voxelbotutils/cogs/utils/__init__.py
voxelbotutils/cogs/utils/analytics_log_handler.py
voxelbotutils/cogs/utils/component_check.py
voxelbotutils/cogs/utils/context_embed.py
voxelbotutils/cogs/utils/custom_bot.py
voxelbotutils/cogs/utils/custom_cog.py
voxelbotutils/cogs/utils/custom_command.py
voxelbotutils/cogs/utils/custom_context.py
voxelbotutils/cogs/utils/embeddify.py
voxelbotutils/cogs/utils/errors.py
voxelbotutils/cogs/utils/help_command.py
voxelbotutils/cogs/utils/missing_required_argument.py
voxelbotutils/cogs/utils/paginator.py
voxelbotutils/cogs/utils/redis.py
voxelbotutils/cogs/utils/settings_menu.py
voxelbotutils/cogs/utils/shard_manager.py
voxelbotutils/cogs/utils/statsd.py
voxelbotutils/cogs/utils/string.py
voxelbotutils/cogs/utils/time_value.py
voxelbotutils/cogs/utils/twitch_stream.py
voxelbotutils/cogs/utils/checks/__init__.py
voxelbotutils/cogs/utils/checks/_slash_commands.py
voxelbotutils/cogs/utils/checks/bot_is_ready.py
voxelbotutils/cogs/utils/checks/is_bot_support.py
voxelbotutils/cogs/utils/checks/is_config_set.py
voxelbotutils/cogs/utils/checks/is_upgrade_chat_subscriber.py
voxelbotutils/cogs/utils/checks/is_voter.py
voxelbotutils/cogs/utils/checks/meta_command.py
voxelbotutils/cogs/utils/checks/_cooldown/__init__.py
voxelbotutils/cogs/utils/checks/_cooldown/cooldown.py
voxelbotutils/cogs/utils/checks/_cooldown/cooldown_with_exemptions.py
voxelbotutils/cogs/utils/checks/_cooldown/role_based_cooldown.py
voxelbotutils-0.8.4.dist-info/LICENSE
voxelbotutils-0.8.4.dist-info/METADATA
voxelbotutils-0.8.4.dist-info/WHEEL
voxelbotutils-0.8.4.dist-info/entry_points.txt
voxelbotutils-0.8.4.dist-info/top_level.txt
voxelbotutils-0.8.4.dist-info/RECORD
