Metadata-Version: 2.1
Name: voxelbotutils
Version: 0.8.4
Summary: A set of bot utilities for Novus
Home-page: https://github.com/Voxel-Fox-Ltd/VoxelBotUtils
Author: Kae Bartlett
Author-email: kae@voxelfox.co.uk
License: UNKNOWN
Platform: UNKNOWN
Classifier: Programming Language :: Python :: 3
Classifier: Programming Language :: Python :: 3.8
Classifier: Programming Language :: Python :: 3.9
Classifier: License :: OSI Approved :: GNU General Public License v2 (GPLv2)
Classifier: Operating System :: OS Independent
Requires-Python: >=3.8
Requires-Dist: novus (>=0.0.8)
Requires-Dist: toml
Requires-Dist: aiosqlite
Requires-Dist: aioredis (<2.0,>=1.3)
Requires-Dist: aioredlock (<0.8,>=0.7.0)
Requires-Dist: aiodogstatsd (<0.15,>=0.14.0)
Requires-Dist: aiohttp
Requires-Dist: upgradechatpy (>=1.0.3<2.0)
Requires-Dist: cryptography
Requires-Dist: aiohttp-jinja2
Requires-Dist: aiohttp-session
Requires-Dist: jinja2 (<4.0.0,>=3.0.0)
Requires-Dist: markdown
Requires-Dist: htmlmin
Provides-Extra: docs
Requires-Dist: sphinx ; extra == 'docs'
Requires-Dist: sphinx-rtd-theme ; extra == 'docs'
Provides-Extra: mysql
Requires-Dist: aiomysql ; extra == 'mysql'
Provides-Extra: postgres
Requires-Dist: asyncpg (<0.22) ; extra == 'postgres'
